data_science_utilities/__init__.py
data_science_utilities/cli.py
data_science_utilities/data_science_utilities.py
data_science_utilities-0.2.4.dist-info/DESCRIPTION.rst
data_science_utilities-0.2.4.dist-info/METADATA
data_science_utilities-0.2.4.dist-info/RECORD
data_science_utilities-0.2.4.dist-info/WHEEL
data_science_utilities-0.2.4.dist-info/entry_points.txt
data_science_utilities-0.2.4.dist-info/metadata.json
data_science_utilities-0.2.4.dist-info/top_level.txt
