Metadata-Version: 2.0
Name: data-science-utilities
Version: 0.2.4
Summary: Data Science utilities in python.
Home-page: https://github.com/truocphamkhac/data-science-utilities
Author: Truoc Pham
Author-email: truoc.phamkhac@asnet.com.vn
License: MIT license
Keywords: data_science_utilities
Platform: UNKNOWN
Classifier: Development Status :: 2 - Pre-Alpha
Classifier: Intended Audience :: Developers
Classifier: License :: OSI Approved :: MIT License
Classifier: Natural Language :: English
Classifier: Programming Language :: Python :: 2
Classifier: Programming Language :: Python :: 2.7
Classifier: Programming Language :: Python :: 3
Classifier: Programming Language :: Python :: 3.4
Classifier: Programming Language :: Python :: 3.5
Classifier: Programming Language :: Python :: 3.6
Requires-Dist: Click (>=6.0)
